[{"playerId":"messi","ovr":96},{"playerId":"ronaldo","ovr":94},{"playerId":"pele","ovr":96},{"playerId":"maradona","ovr":95},{"playerId":"zidane","ovr":94},{"playerId":"cruyff","ovr":94},{"playerId":"di-stefano","ovr":94},{"playerId":"ronaldinho","ovr":93},{"playerId":"r9","ovr":94},{"playerId":"maldini","ovr":94},{"playerId":"henry","ovr":91},{"playerId":"modric","ovr":89},{"playerId":"benzema","ovr":90},{"playerId":"lewandowski","ovr":90},{"playerId":"van-dijk","ovr":90},{"playerId":"salah","ovr":89},{"playerId":"neymar","ovr":89},{"playerId":"bellingham","ovr":88},{"playerId":"xavi","ovr":91},{"playerId":"iniesta","ovr":91},{"playerId":"busquets","ovr":88},{"playerId":"pique","ovr":87},{"playerId":"ramos","ovr":89},{"playerId":"casillas","ovr":90},{"playerId":"buffon","ovr":92},{"playerId":"neuer","ovr":91},{"playerId":"ter-stegen","ovr":89},{"playerId":"de-bruyne","ovr":91},{"playerId":"mbappe","ovr":91},{"playerId":"haaland","ovr":90},{"playerId":"kane","ovr":89},{"playerId":"son","ovr":87},{"playerId":"mane","ovr":88},{"playerId":"firmino","ovr":86},{"playerId":"sane","ovr":86},{"playerId":"gundogan","ovr":87},{"playerId":"kroos","ovr":89},{"playerId":"casemiro","ovr":88},{"playerId":"bale","ovr":87},{"playerId":"suarez","ovr":90},{"playerId":"aguero","ovr":89},{"playerId":"torres","ovr":88},{"playerId":"villa","ovr":87},{"playerId":"xabi-alonso","ovr":88},{"playerId":"gerrard","ovr":89},{"playerId":"lampard","ovr":88},{"playerId":"scholes","ovr":89},{"playerId":"giggs","ovr":88},{"playerId":"rooney","ovr":88},{"playerId":"beckham","ovr":89},{"playerId":"bergkamp","ovr":91},{"playerId":"cantona","ovr":88},{"playerId":"best","ovr":90},{"playerId":"charlton","ovr":91},{"playerId":"moore","ovr":88},{"playerId":"lineker","ovr":86},{"playerId":"shearer","ovr":87},{"playerId":"drogba","ovr":88},{"playerId":"essien","ovr":86},{"playerId":"makelele","ovr":87},{"playerId":"kaka","ovr":90},{"playerId":"rivaldo","ovr":89},{"playerId":"romario","ovr":91},{"playerId":"cafu","ovr":90},{"playerId":"carlos","ovr":88},{"playerId":"roberto-carlos","ovr":90},{"playerId":"marcelo","ovr":87},{"playerId":"alves","ovr":86},{"playerId":"maicon","ovr":85},{"playerId":"trent","ovr":87},{"playerId":"robertson","ovr":86},{"playerId":"cancelo","ovr":87},{"playerId":"walker","ovr":86},{"playerId":"stones","ovr":86},{"playerId":"dias","ovr":88},{"playerId":"vidic","ovr":87},{"playerId":"ferdinand","ovr":88},{"playerId":"nesta","ovr":91},{"playerId":"baresi","ovr":93},{"playerId":"beckenbauer","ovr":94},{"playerId":"muller","ovr":92},{"playerId":"matthaus","ovr":92},{"playerId":"klinsmann","ovr":88},{"playerId":"lahm","ovr":88},{"playerId":"schweinsteiger","ovr":88},{"playerId":"ballack","ovr":87},{"playerId":"klose","ovr":87},{"playerId":"podolski","ovr":84},{"playerId":"pirlo","ovr":91},{"playerId":"totti","ovr":90},{"playerId":"del-piero","ovr":90},{"playerId":"Cannavaro","ovr":89},{"playerId":"gattuso","ovr":86},{"playerId":"seedorf","ovr":87},{"playerId":"shevchenko","ovr":89},{"playerId":"vieira","ovr":88},{"playerId":"petit","ovr":87},{"playerId":"thuram","ovr":88},{"playerId":"figo","ovr":89},{"playerId":"ronaldo-brazil","ovr":94},{"playerId":"adriano","ovr":86},{"playerId":"vini-jr","ovr":89},{"playerId":"rodrygo","ovr":86},{"playerId":"endrick","ovr":82},{"playerId":"pedri","ovr":87},{"playerId":"gavi","ovr":86},{"playerId":"yamal","ovr":84},{"playerId":"musiala","ovr":87},{"playerId":"wirtz","ovr":86},{"playerId":"foden","ovr":87},{"playerId":"palmer","ovr":85},{"playerId":"rice","ovr":87},{"playerId":"saka","ovr":87},{"playerId":"martinelli","ovr":85},{"playerId":"odegaard","ovr":86},{"playerId":"bruno-fernandes","ovr":87},{"playerId":"rashford","ovr":85},{"playerId":"sancho","ovr":84},{"playerId":"antony","ovr":82},{"playerId":"mount","ovr":84},{"playerId":"pogba","ovr":86},{"playerId":"varane","ovr":87},{"playerId":"kante","ovr":88},{"playerId":"hazard","ovr":89},{"playerId":"courtois","ovr":90},{"playerId":"de-gea","ovr":87},{"playerId":"alisson","ovr":89},{"playerId":"ederson","ovr":88},{"playerId":"dibu","ovr":88},{"playerId":"emiliano-martinez","ovr":88},{"playerId":"yashin","ovr":95},{"playerId":"lev-yashin","ovr":95},{"playerId":"platini","ovr":93},{"playerId":"papin","ovr":86},{"playerId":"gullit","ovr":91},{"playerId":"van-basten","ovr":92},{"playerId":"rijkaard","ovr":90},{"playerId":"koeman","ovr":87},{"playerId":"stoichkov","ovr":88},{"playerId":"hagi","ovr":90},{"playerId":"souness","ovr":86},{"playerId":"dalglish","ovr":90},{"playerId":"kenny-dalglish","ovr":90},{"playerId":"owen","ovr":86},{"playerId":"tevez","ovr":86},{"playerId":"higuain","ovr":85},{"playerId":"dybala","ovr":86},{"playerId":"icardi","ovr":85},{"playerId":"lautaro","ovr":87},{"playerId":"di-maria","ovr":88},{"playerId":"mascherano","ovr":86},{"playerId":"batistuta","ovr":89},{"playerId":"crespo","ovr":87},{"playerId":"aimar","ovr":86},{"playerId":"saviola","ovr":85},{"playerId":"forlan","ovr":87},{"playerId":"cavani","ovr":86},{"playerId":"falcao","ovr":87},{"playerId":"james","ovr":85},{"playerId":"james-rodriguez","ovr":85},{"playerId":"valderrama","ovr":88},{"playerId":"carlos-valderrama","ovr":88},{"playerId":"asprilla","ovr":84},{"playerId":"renaldinho","ovr":93}]